{
  "$schema": "https://tree-sitter.github.io/tree-sitter/assets/schemas/grammar.schema.json",
  "name": "confluence_wiki",
  "rules": {
    "document": {
      "type": "REPEAT",
      "content": {
        "type": "SYMBOL",
        "name": "_block"
      }
    },
    "_block": {
      "type": "PREC",
      "value": 5,
      "content": {
        "type": "CHOICE",
        "members": [
          {
            "type": "SYMBOL",
            "name": "numbered_list"
          },
          {
            "type": "SYMBOL",
            "name": "bullet_list"
          },
          {
            "type": "SYMBOL",
            "name": "heading"
          },
          {
            "type": "SYMBOL",
            "name": "_paragraph"
          },
          {
            "type": "SYMBOL",
            "name": "code_block"
          },
          {
            "type": "SYMBOL",
            "name": "panel_block"
          },
          {
            "type": "SYMBOL",
            "name": "quote_block"
          },
          {
            "type": "SYMBOL",
            "name": "table"
          }
        ]
      }
    },
    "numbered_list": {
      "type": "PREC_LEFT",
      "value": 0,
      "content": {
        "type": "SEQ",
        "members": [
          {
            "type": "REPEAT1",
            "content": {
              "type": "SYMBOL",
              "name": "numbered_list_item"
            }
          },
          {
            "type": "STRING",
            "value": "\n\n"
          }
        ]
      }
    },
    "numbered_list_item": {
      "type": "PREC_LEFT",
      "value": 0,
      "content": {
        "type": "SEQ",
        "members": [
          {
            "type": "STRING",
            "value": "# "
          },
          {
            "type": "REPEAT",
            "content": {
              "type": "SYMBOL",
              "name": "_inline_content"
            }
          }
        ]
      }
    },
    "bullet_list": {
      "type": "PREC_LEFT",
      "value": 0,
      "content": {
        "type": "SEQ",
        "members": [
          {
            "type": "REPEAT1",
            "content": {
              "type": "CHOICE",
              "members": [
                {
                  "type": "SYMBOL",
                  "name": "bullet_list_item1"
                },
                {
                  "type": "SYMBOL",
                  "name": "bullet_list_item2"
                },
                {
                  "type": "SYMBOL",
                  "name": "bullet_list_item3"
                },
                {
                  "type": "SYMBOL",
                  "name": "bullet_list_item4"
                },
                {
                  "type": "SYMBOL",
                  "name": "bullet_list_item5"
                }
              ]
            }
          },
          {
            "type": "STRING",
            "value": "\n\n"
          }
        ]
      }
    },
    "bullet_list_item1": {
      "type": "PREC_LEFT",
      "value": 0,
      "content": {
        "type": "SEQ",
        "members": [
          {
            "type": "STRING",
            "value": "* "
          },
          {
            "type": "REPEAT",
            "content": {
              "type": "SYMBOL",
              "name": "_inline_content"
            }
          }
        ]
      }
    },
    "bullet_list_item2": {
      "type": "PREC_LEFT",
      "value": 0,
      "content": {
        "type": "SEQ",
        "members": [
          {
            "type": "STRING",
            "value": "** "
          },
          {
            "type": "REPEAT",
            "content": {
              "type": "SYMBOL",
              "name": "_inline_content"
            }
          }
        ]
      }
    },
    "bullet_list_item3": {
      "type": "PREC_LEFT",
      "value": 0,
      "content": {
        "type": "SEQ",
        "members": [
          {
            "type": "STRING",
            "value": "*** "
          },
          {
            "type": "REPEAT",
            "content": {
              "type": "SYMBOL",
              "name": "_inline_content"
            }
          }
        ]
      }
    },
    "bullet_list_item4": {
      "type": "PREC_LEFT",
      "value": 0,
      "content": {
        "type": "SEQ",
        "members": [
          {
            "type": "STRING",
            "value": "**** "
          },
          {
            "type": "REPEAT",
            "content": {
              "type": "SYMBOL",
              "name": "_inline_content"
            }
          }
        ]
      }
    },
    "bullet_list_item5": {
      "type": "PREC_LEFT",
      "value": 0,
      "content": {
        "type": "SEQ",
        "members": [
          {
            "type": "STRING",
            "value": "***** "
          },
          {
            "type": "REPEAT",
            "content": {
              "type": "SYMBOL",
              "name": "_inline_content"
            }
          }
        ]
      }
    },
    "heading": {
      "type": "CHOICE",
      "members": [
        {
          "type": "SYMBOL",
          "name": "h1_heading"
        },
        {
          "type": "SYMBOL",
          "name": "h2_heading"
        },
        {
          "type": "SYMBOL",
          "name": "h3_heading"
        },
        {
          "type": "SYMBOL",
          "name": "h4_heading"
        },
        {
          "type": "SYMBOL",
          "name": "h5_heading"
        },
        {
          "type": "SYMBOL",
          "name": "h6_heading"
        }
      ]
    },
    "h1_heading": {
      "type": "PREC_RIGHT",
      "value": 0,
      "content": {
        "type": "SEQ",
        "members": [
          {
            "type": "STRING",
            "value": "h1. "
          },
          {
            "type": "REPEAT",
            "content": {
              "type": "SYMBOL",
              "name": "_inline_content"
            }
          },
          {
            "type": "STRING",
            "value": "\n"
          }
        ]
      }
    },
    "h2_heading": {
      "type": "PREC_RIGHT",
      "value": 0,
      "content": {
        "type": "SEQ",
        "members": [
          {
            "type": "STRING",
            "value": "h2. "
          },
          {
            "type": "REPEAT",
            "content": {
              "type": "SYMBOL",
              "name": "_inline_content"
            }
          },
          {
            "type": "STRING",
            "value": "\n"
          }
        ]
      }
    },
    "h3_heading": {
      "type": "PREC_RIGHT",
      "value": 0,
      "content": {
        "type": "SEQ",
        "members": [
          {
            "type": "STRING",
            "value": "h3. "
          },
          {
            "type": "REPEAT",
            "content": {
              "type": "SYMBOL",
              "name": "_inline_content"
            }
          },
          {
            "type": "STRING",
            "value": "\n"
          }
        ]
      }
    },
    "h4_heading": {
      "type": "PREC_RIGHT",
      "value": 0,
      "content": {
        "type": "SEQ",
        "members": [
          {
            "type": "STRING",
            "value": "h4. "
          },
          {
            "type": "REPEAT",
            "content": {
              "type": "SYMBOL",
              "name": "_inline_content"
            }
          },
          {
            "type": "STRING",
            "value": "\n"
          }
        ]
      }
    },
    "h5_heading": {
      "type": "PREC_RIGHT",
      "value": 0,
      "content": {
        "type": "SEQ",
        "members": [
          {
            "type": "STRING",
            "value": "h5. "
          },
          {
            "type": "REPEAT",
            "content": {
              "type": "SYMBOL",
              "name": "_inline_content"
            }
          },
          {
            "type": "STRING",
            "value": "\n"
          }
        ]
      }
    },
    "h6_heading": {
      "type": "PREC_RIGHT",
      "value": 0,
      "content": {
        "type": "SEQ",
        "members": [
          {
            "type": "STRING",
            "value": "h6. "
          },
          {
            "type": "REPEAT",
            "content": {
              "type": "SYMBOL",
              "name": "_inline_content"
            }
          },
          {
            "type": "STRING",
            "value": "\n"
          }
        ]
      }
    },
    "_paragraph": {
      "type": "PREC_LEFT",
      "value": 0,
      "content": {
        "type": "REPEAT1",
        "content": {
          "type": "SYMBOL",
          "name": "_inline_content"
        }
      }
    },
    "_inline_content": {
      "type": "CHOICE",
      "members": [
        {
          "type": "SYMBOL",
          "name": "bold"
        },
        {
          "type": "SYMBOL",
          "name": "color"
        },
        {
          "type": "SYMBOL",
          "name": "image"
        },
        {
          "type": "SYMBOL",
          "name": "italic"
        },
        {
          "type": "SYMBOL",
          "name": "link"
        },
        {
          "type": "SYMBOL",
          "name": "monospace"
        },
        {
          "type": "SYMBOL",
          "name": "text"
        },
        {
          "type": "SYMBOL",
          "name": "url"
        }
      ]
    },
    "text": {
      "type": "PREC",
      "value": -1,
      "content": {
        "type": "PATTERN",
        "value": "[^*_\\s{}!\\[\\]|]+"
      }
    },
    "bold": {
      "type": "SEQ",
      "members": [
        {
          "type": "STRING",
          "value": "*"
        },
        {
          "type": "REPEAT",
          "content": {
            "type": "PATTERN",
            "value": "[^*]"
          }
        },
        {
          "type": "STRING",
          "value": "*"
        }
      ]
    },
    "italic": {
      "type": "PREC_RIGHT",
      "value": 0,
      "content": {
        "type": "SEQ",
        "members": [
          {
            "type": "PATTERN",
            "value": " _[^_]"
          },
          {
            "type": "REPEAT1",
            "content": {
              "type": "SYMBOL",
              "name": "text"
            }
          },
          {
            "type": "STRING",
            "value": "_"
          }
        ]
      }
    },
    "monospace": {
      "type": "SEQ",
      "members": [
        {
          "type": "STRING",
          "value": "{{"
        },
        {
          "type": "REPEAT",
          "content": {
            "type": "PATTERN",
            "value": "[^{]"
          }
        },
        {
          "type": "PREC",
          "value": 2,
          "content": {
            "type": "STRING",
            "value": "}}"
          }
        }
      ]
    },
    "url": {
      "type": "PATTERN",
      "value": "https?:\\/\\/[^\\s\\]]+"
    },
    "image": {
      "type": "SEQ",
      "members": [
        {
          "type": "STRING",
          "value": "!"
        },
        {
          "type": "PATTERN",
          "value": "[a-zA-Z.][^\\|!]+"
        },
        {
          "type": "CHOICE",
          "members": [
            {
              "type": "SEQ",
              "members": [
                {
                  "type": "STRING",
                  "value": "|"
                },
                {
                  "type": "PATTERN",
                  "value": "[^\\|!]+"
                }
              ]
            },
            {
              "type": "BLANK"
            }
          ]
        },
        {
          "type": "STRING",
          "value": "!"
        }
      ]
    },
    "link": {
      "type": "SEQ",
      "members": [
        {
          "type": "STRING",
          "value": "["
        },
        {
          "type": "PATTERN",
          "value": "[^\\|\\]]+"
        },
        {
          "type": "CHOICE",
          "members": [
            {
              "type": "SEQ",
              "members": [
                {
                  "type": "STRING",
                  "value": "|"
                },
                {
                  "type": "PATTERN",
                  "value": "[^\\|\\]]+"
                }
              ]
            },
            {
              "type": "BLANK"
            }
          ]
        },
        {
          "type": "STRING",
          "value": "]"
        }
      ]
    },
    "colorcode": {
      "type": "PREC",
      "value": -1,
      "content": {
        "type": "PATTERN",
        "value": "[a-zA-Z#0-9]+"
      }
    },
    "color_start": {
      "type": "SEQ",
      "members": [
        {
          "type": "STRING",
          "value": "{color:"
        },
        {
          "type": "SYMBOL",
          "name": "colorcode"
        },
        {
          "type": "STRING",
          "value": "}"
        }
      ]
    },
    "color_end": {
      "type": "STRING",
      "value": "{color}"
    },
    "color": {
      "type": "SEQ",
      "members": [
        {
          "type": "SYMBOL",
          "name": "color_start"
        },
        {
          "type": "REPEAT",
          "content": {
            "type": "SYMBOL",
            "name": "_inline_content"
          }
        },
        {
          "type": "SYMBOL",
          "name": "color_end"
        }
      ]
    },
    "language": {
      "type": "PATTERN",
      "value": "[a-z]+"
    },
    "code_start": {
      "type": "PREC",
      "value": 9,
      "content": {
        "type": "SEQ",
        "members": [
          {
            "type": "STRING",
            "value": "{code"
          },
          {
            "type": "CHOICE",
            "members": [
              {
                "type": "SEQ",
                "members": [
                  {
                    "type": "STRING",
                    "value": ":"
                  },
                  {
                    "type": "SYMBOL",
                    "name": "language"
                  }
                ]
              },
              {
                "type": "BLANK"
              }
            ]
          },
          {
            "type": "STRING",
            "value": "}"
          }
        ]
      }
    },
    "code_end": {
      "type": "PREC",
      "value": 20,
      "content": {
        "type": "STRING",
        "value": "{code}"
      }
    },
    "code_body": {
      "type": "REPEAT1",
      "content": {
        "type": "PREC",
        "value": 5,
        "content": {
          "type": "PATTERN",
          "value": "."
        }
      }
    },
    "js_code_start": {
      "type": "PREC",
      "value": 9,
      "content": {
        "type": "STRING",
        "value": "{code:js}"
      }
    },
    "js_code_body": {
      "type": "REPEAT1",
      "content": {
        "type": "PREC",
        "value": 5,
        "content": {
          "type": "PATTERN",
          "value": "."
        }
      }
    },
    "js_code_block": {
      "type": "SEQ",
      "members": [
        {
          "type": "SYMBOL",
          "name": "js_code_start"
        },
        {
          "type": "SYMBOL",
          "name": "js_code_body"
        },
        {
          "type": "SYMBOL",
          "name": "code_end"
        }
      ]
    },
    "json_code_start": {
      "type": "PREC",
      "value": 9,
      "content": {
        "type": "STRING",
        "value": "{code:json}"
      }
    },
    "json_code_body": {
      "type": "REPEAT1",
      "content": {
        "type": "PREC",
        "value": 5,
        "content": {
          "type": "PATTERN",
          "value": "."
        }
      }
    },
    "json_code_block": {
      "type": "SEQ",
      "members": [
        {
          "type": "SYMBOL",
          "name": "json_code_start"
        },
        {
          "type": "SYMBOL",
          "name": "json_code_body"
        },
        {
          "type": "SYMBOL",
          "name": "code_end"
        }
      ]
    },
    "python_code_start": {
      "type": "PREC",
      "value": 9,
      "content": {
        "type": "STRING",
        "value": "{code:python}"
      }
    },
    "python_code_body": {
      "type": "REPEAT1",
      "content": {
        "type": "PREC",
        "value": 5,
        "content": {
          "type": "PATTERN",
          "value": "."
        }
      }
    },
    "python_code_block": {
      "type": "SEQ",
      "members": [
        {
          "type": "SYMBOL",
          "name": "python_code_start"
        },
        {
          "type": "SYMBOL",
          "name": "python_code_body"
        },
        {
          "type": "SYMBOL",
          "name": "code_end"
        }
      ]
    },
    "bash_code_start": {
      "type": "PREC",
      "value": 9,
      "content": {
        "type": "STRING",
        "value": "{code:bash}"
      }
    },
    "bash_code_body": {
      "type": "REPEAT1",
      "content": {
        "type": "PREC",
        "value": 5,
        "content": {
          "type": "PATTERN",
          "value": "."
        }
      }
    },
    "bash_code_block": {
      "type": "SEQ",
      "members": [
        {
          "type": "SYMBOL",
          "name": "bash_code_start"
        },
        {
          "type": "SYMBOL",
          "name": "bash_code_body"
        },
        {
          "type": "SYMBOL",
          "name": "code_end"
        }
      ]
    },
    "sh_code_start": {
      "type": "PREC",
      "value": 9,
      "content": {
        "type": "STRING",
        "value": "{code:sh}"
      }
    },
    "sh_code_body": {
      "type": "REPEAT1",
      "content": {
        "type": "PREC",
        "value": 5,
        "content": {
          "type": "PATTERN",
          "value": "."
        }
      }
    },
    "sh_code_block": {
      "type": "SEQ",
      "members": [
        {
          "type": "SYMBOL",
          "name": "sh_code_start"
        },
        {
          "type": "SYMBOL",
          "name": "sh_code_body"
        },
        {
          "type": "SYMBOL",
          "name": "code_end"
        }
      ]
    },
    "base_code_block": {
      "type": "SEQ",
      "members": [
        {
          "type": "SYMBOL",
          "name": "code_start"
        },
        {
          "type": "SYMBOL",
          "name": "code_body"
        },
        {
          "type": "SYMBOL",
          "name": "code_end"
        }
      ]
    },
    "key_value": {
      "type": "PREC_LEFT",
      "value": 0,
      "content": {
        "type": "SEQ",
        "members": [
          {
            "type": "CHOICE",
            "members": [
              {
                "type": "STRING",
                "value": "|"
              },
              {
                "type": "BLANK"
              }
            ]
          },
          {
            "type": "PATTERN",
            "value": "[a-zA-Z]+"
          },
          {
            "type": "STRING",
            "value": "="
          },
          {
            "type": "PATTERN",
            "value": "[^|}]+"
          }
        ]
      }
    },
    "panel_block": {
      "type": "PREC_RIGHT",
      "value": 0,
      "content": {
        "type": "SEQ",
        "members": [
          {
            "type": "STRING",
            "value": "{panel"
          },
          {
            "type": "CHOICE",
            "members": [
              {
                "type": "SEQ",
                "members": [
                  {
                    "type": "STRING",
                    "value": ":"
                  },
                  {
                    "type": "REPEAT1",
                    "content": {
                      "type": "SYMBOL",
                      "name": "key_value"
                    }
                  }
                ]
              },
              {
                "type": "BLANK"
              }
            ]
          },
          {
            "type": "STRING",
            "value": "}"
          },
          {
            "type": "REPEAT",
            "content": {
              "type": "SYMBOL",
              "name": "_block"
            }
          },
          {
            "type": "STRING",
            "value": "{panel}"
          }
        ]
      }
    },
    "quote_block": {
      "type": "SEQ",
      "members": [
        {
          "type": "STRING",
          "value": "{quote}"
        },
        {
          "type": "REPEAT",
          "content": {
            "type": "SYMBOL",
            "name": "_inline_content"
          }
        },
        {
          "type": "STRING",
          "value": "{quote}"
        }
      ]
    },
    "code_block": {
      "type": "CHOICE",
      "members": [
        {
          "type": "SYMBOL",
          "name": "base_code_block"
        },
        {
          "type": "SYMBOL",
          "name": "js_code_block"
        },
        {
          "type": "SYMBOL",
          "name": "json_code_block"
        },
        {
          "type": "SYMBOL",
          "name": "python_code_block"
        },
        {
          "type": "SYMBOL",
          "name": "bash_code_block"
        },
        {
          "type": "SYMBOL",
          "name": "sh_code_block"
        }
      ]
    },
    "table": {
      "type": "PREC_RIGHT",
      "value": 0,
      "content": {
        "type": "SEQ",
        "members": [
          {
            "type": "REPEAT",
            "content": {
              "type": "SYMBOL",
              "name": "table_header"
            }
          },
          {
            "type": "REPEAT1",
            "content": {
              "type": "SEQ",
              "members": [
                {
                  "type": "SYMBOL",
                  "name": "table_row"
                },
                {
                  "type": "STRING",
                  "value": "\n"
                }
              ]
            }
          }
        ]
      }
    },
    "table_header": {
      "type": "PREC_LEFT",
      "value": 0,
      "content": {
        "type": "SEQ",
        "members": [
          {
            "type": "STRING",
            "value": "||"
          },
          {
            "type": "REPEAT1",
            "content": {
              "type": "SEQ",
              "members": [
                {
                  "type": "SYMBOL",
                  "name": "table_header_cell"
                },
                {
                  "type": "STRING",
                  "value": "||"
                }
              ]
            }
          }
        ]
      }
    },
    "table_row": {
      "type": "PREC_LEFT",
      "value": 0,
      "content": {
        "type": "SEQ",
        "members": [
          {
            "type": "STRING",
            "value": "|"
          },
          {
            "type": "REPEAT1",
            "content": {
              "type": "SEQ",
              "members": [
                {
                  "type": "SYMBOL",
                  "name": "table_cell"
                },
                {
                  "type": "STRING",
                  "value": "|"
                }
              ]
            }
          }
        ]
      }
    },
    "table_cell": {
      "type": "REPEAT1",
      "content": {
        "type": "SYMBOL",
        "name": "_inline_content"
      }
    },
    "table_header_cell": {
      "type": "PATTERN",
      "value": "[^|]+"
    }
  },
  "extras": [
    {
      "type": "PATTERN",
      "value": "[\\s]"
    }
  ],
  "conflicts": [],
  "precedences": [
    [
      {
        "type": "STRING",
        "value": "heading"
      },
      {
        "type": "STRING",
        "value": "block"
      },
      {
        "type": "STRING",
        "value": "table"
      },
      {
        "type": "STRING",
        "value": "panel_block"
      },
      {
        "type": "STRING",
        "value": "quote_block"
      },
      {
        "type": "STRING",
        "value": "code_block"
      },
      {
        "type": "STRING",
        "value": "bullet_list"
      },
      {
        "type": "STRING",
        "value": "numbered_list_item"
      },
      {
        "type": "STRING",
        "value": "_paragraph"
      },
      {
        "type": "STRING",
        "value": "inline"
      },
      {
        "type": "STRING",
        "value": "bold"
      },
      {
        "type": "STRING",
        "value": "italic"
      },
      {
        "type": "STRING",
        "value": "monospace"
      },
      {
        "type": "STRING",
        "value": "url"
      },
      {
        "type": "STRING",
        "value": "color"
      },
      {
        "type": "STRING",
        "value": "image"
      },
      {
        "type": "STRING",
        "value": "link"
      },
      {
        "type": "STRING",
        "value": "text"
      }
    ]
  ],
  "externals": [],
  "inline": [],
  "supertypes": [],
  "reserved": {}
}